<!-- This is a generated file. It is highly recommended that you DO NOT edit this file. --><iq:manifest xmlns:iq="http://www.garmin.com/xml/connectiq" version="1">
    <iq:application entry="ZWaveRemoteApp" id="A45DEA90522942578DE6F48D4FBFA65F" launcherIcon="@Drawables.LauncherIcon" name="@Strings.AppName" type="watch-app">

        <iq:products>
            <iq:product id="round_watch"/>
            <iq:product id="fenix3_hr"/>
        </iq:products>

        <iq:permissions>
            <iq:uses-permission id="Communications"/>
        </iq:permissions>

        <iq:languages/>

    </iq:application>
</iq:manifest>
